GridPowerSAE/__init__.py
GridPowerSAE/main.py
tests/__init__.py
tests/test_run_rastr_win.py
GridPowerSAE-0.1.0.dist-info/LICENSE
GridPowerSAE-0.1.0.dist-info/METADATA
GridPowerSAE-0.1.0.dist-info/WHEEL
GridPowerSAE-0.1.0.dist-info/entry_points.txt
GridPowerSAE-0.1.0.dist-info/top_level.txt
GridPowerSAE-0.1.0.dist-info/RECORD
